inspector/__init__.py
inspector/apps.py
inspector/management/__init__.py
inspector/management/commands/__init__.py
inspector/management/commands/constants.py
inspector/management/commands/inspectmigrations.py
django_migration_inspector-0.0.3.dist-info/LICENSE
django_migration_inspector-0.0.3.dist-info/METADATA
django_migration_inspector-0.0.3.dist-info/WHEEL
django_migration_inspector-0.0.3.dist-info/top_level.txt
django_migration_inspector-0.0.3.dist-info/RECORD
