Metadata-Version: 2.1
Name: django-migration-inspector
Version: 0.0.3
Summary: Django extension to inspect validity of migration files
Author-email: Samarth Parnami <samarthparnami@gmail.com>
Project-URL: Homepage, https://github.com/SamarthParnami/django-migration-inspector
Project-URL: Issues, https://github.com/SamarthParnami/django-migration-inspector/issues
Classifier: Programming Language :: Python :: 3
Classifier: License :: OSI Approved :: BSD License
Classifier: Operating System :: OS Independent
Requires-Python: >=3.6
License-File: LICENSE
Requires-Dist: django >=3.2.0
